LICENSE
MANIFEST.in
README.md
setup.py
src/wheezy/__init__.py
src/wheezy.caching.egg-info/PKG-INFO
src/wheezy.caching.egg-info/SOURCES.txt
src/wheezy.caching.egg-info/dependency_links.txt
src/wheezy.caching.egg-info/namespace_packages.txt
src/wheezy.caching.egg-info/not-zip-safe
src/wheezy.caching.egg-info/requires.txt
src/wheezy.caching.egg-info/top_level.txt
src/wheezy/caching/__init__.py
src/wheezy/caching/client.py
src/wheezy/caching/dependency.py
src/wheezy/caching/encoding.py
src/wheezy/caching/lockout.py
src/wheezy/caching/logging.py
src/wheezy/caching/memcache.py
src/wheezy/caching/memory.py
src/wheezy/caching/null.py
src/wheezy/caching/patterns.py
src/wheezy/caching/pylibmc.py
src/wheezy/caching/utils.py